[
    {
        "url": "https://www.tripadvisor.com/Restaurant_Review-g60898-d846532-Reviews-Big_Easy_Grille-Atlanta_Georgia.html",
        "imgs": "[\"https://media-cdn.tripadvisor.com/media/photo-f/18/ef/98/52/photo0jpg.jpg\", \"https://media-cdn.tripadvisor.com/media/photo-s/14/3c/64/90/big-easy-grille-atlanta.jpg\"]",
        "name": "Big Easy Grille",
        "address": "1193 Collier Rd NW Ste E, Atlanta, GA 30318-8265",
        "phone": "+1 404-352-2777",
        "id": "6875387284589664",
        "rating": 4.5,
        "review_count": 40,
        "tags": "[\"Mid-range\", \"American\", \"Cajun & Creole\", \"Bar\"]",
        "price": "$$ - $$$"
    },
    {
        "url": "https://www.tripadvisor.com/Restaurant_Review-g60898-d2045862-Reviews-Kaleidoscope_Bistro_and_Pub-Atlanta_Georgia.html",
        "imgs": "[\"https://media-cdn.tripadvisor.com/media/photo-f/12/5e/06/52/20180317-122837-largejpg.jpg\", \"https://media-cdn.tripadvisor.com/media/photo-s/03/a2/ad/17/kaleidoscope-bistro-and.jpg\"]",
        "name": "Kaleidoscope Bistro and Pub",
        "address": "1410 Dresden Dr NE Ste 100, Atlanta, GA 30319-3526",
        "phone": "+1 404-474-9600",
        "id": "4330167649529095",
        "rating": 4,
        "review_count": 117,
        "tags": "[\"Mid-range\", \"American\", \"Bar\", \"Gluten Free Options\"]",
        "price": "$$ - $$$"
    },
    {
        "url": "https://www.tripadvisor.com/Restaurant_Review-g60898-d532918-Reviews-Pho_Bac-Atlanta_Georgia.html",
        "imgs": "[\"https://media-cdn.tripadvisor.com/media/photo-f/0c/4d/f2/51/photo1jpg.jpg\", \"https://media-cdn.tripadvisor.com/media/photo-s/07/43/a1/19/cover-photo.jpg\"]",
        "name": "Pho Bac",
        "address": "4897 Buford Highway Northeast #105, Atlanta, GA 30341-3667",
        "phone": "+1 770-986-4273",
        "id": "2441167363398471",
        "rating": 4.5,
        "review_count": 55,
        "tags": "[\"Cheap Eats\", \"Asian\", \"Vietnamese\", \"Soups\"]",
        "price": "$"
    },
    {
        "url": "https://www.tripadvisor.com/Restaurant_Review-g60898-d8858208-Reviews-Hop_City_Craft_Beer_Wine-Atlanta_Georgia.html",
        "imgs": "[\"https://media-cdn.tripadvisor.com/media/photo-s/19/fd/e0/d8/20191109-170256-largejpg.jpg\", \"https://media-cdn.tripadvisor.com/media/photo-f/0f/76/16/69/photo1jpg.jpg\"]",
        "name": "Hop City Craft Beer & Wine",
        "address": "99 Krog St NE Suite D, Atlanta, GA 30307-2677",
        "phone": "+1 470-355-2534",
        "id": "4353251344917187",
        "rating": 4,
        "review_count": 45,
        "tags": "[\"Mid-range\", \"Wine Bar\"]",
        "price": "$$ - $$$"
    },
    {
        "url": "https://www.tripadvisor.com/Restaurant_Review-g60898-d10108997-Reviews-Biltong_Bar-Atlanta_Georgia.html",
        "imgs": "[\"https://media-cdn.tripadvisor.com/media/photo-s/1a/76/2f/e9/biltong-bar.jpg\", \"https://media-cdn.tripadvisor.com/media/photo-s/0a/f8/62/dd/garlic-beef-jerky.jpg\"]",
        "name": "Biltong Bar",
        "address": "675 Ponce de Leon Ave NE, Atlanta, GA 30308-1884",
        "phone": "+1 678-515-0620",
        "id": "8436477243599470",
        "rating": 4.5,
        "review_count": 32,
        "tags": "[\"Mid-range\", \"American\", \"African\", \"Bar\"]",
        "price": "$$ - $$$"
    },
    {
        "url": "https://www.tripadvisor.com/Restaurant_Review-g60898-d4039146-Reviews-The_One_Sushi-Atlanta_Georgia.html",
        "imgs": "[\"https://media-cdn.tripadvisor.com/media/photo-s/1c/77/76/83/20201227-185209-largejpg.jpg\", \"https://media-cdn.tripadvisor.com/media/photo-f/04/cd/e7/97/black-cod-platter.jpg\"]",
        "name": "The One Sushi +",
        "address": "2523 Caldwell Rd NE Suite 1000, Atlanta, GA 30319-3116",
        "phone": "+1 404-869-6988",
        "id": "4489652527352361",
        "rating": 4.5,
        "review_count": 47,
        "tags": "[\"Mid-range\", \"Japanese\", \"Sushi\", \"Asian\"]",
        "price": "$$ - $$$"
    },
    {
        "url": "https://www.tripadvisor.com/Restaurant_Review-g60898-d8619687-Reviews-Restaurant_356-Atlanta_Georgia.html",
        "imgs": "[\"https://media-cdn.tripadvisor.com/media/photo-f/14/b2/f0/05/the-356-restaurant-inside.jpg\", \"https://media-cdn.tripadvisor.com/media/photo-s/09/33/f6/68/photo0jpg.jpg\"]",
        "name": "Restaurant 356",
        "address": "1 Porsche Dr, Atlanta, GA 30354-1654",
        "phone": "+1 770-290-4356",
        "id": "3811165867755645",
        "rating": 4,
        "review_count": 62,
        "tags": "[\"Fine Dining\", \"American\", \"Vegetarian Friendly\"]",
        "price": "$$$$"
    },
    {
        "url": "https://www.tripadvisor.com/Restaurant_Review-g60898-d10019839-Reviews-The_Brass_Tap-Atlanta_Georgia.html",
        "imgs": "[\"https://media-cdn.tripadvisor.com/media/photo-s/1c/b1/be/bf/fb-img-1614613241371.jpg\", \"https://media-cdn.tripadvisor.com/media/photo-f/0e/4a/8a/8d/everything-we-ordered.jpg\"]",
        "name": "The Brass Tap",
        "address": "4505 Ashford Dunwoody Rd NE, Atlanta, GA 30346-1514",
        "phone": "+1 770-557-0232",
        "id": "9048697312824136",
        "rating": 4.5,
        "review_count": 38,
        "tags": "[\"Mid-range\", \"American\", \"Bar\", \"Pub\"]",
        "price": "$$ - $$$"
    },
    {
        "url": "https://www.tripadvisor.com/Restaurant_Review-g60898-d435967-Reviews-Ted_s_Montana_Grill-Atlanta_Georgia.html",
        "imgs": "[\"https://media-cdn.tripadvisor.com/media/photo-f/16/15/c1/3b/interior-ted-s-montana.jpg\", \"https://media-cdn.tripadvisor.com/media/photo-f/03/e0/45/f5/so-schaut-s-aus.jpg\"]",
        "name": "Ted's Montana Grill",
        "address": "640 Johnson Ferry Rd, Atlanta, GA 30068-4664",
        "phone": "+1 770-578-8337",
        "id": "6098508917426854",
        "rating": 4,
        "review_count": 67,
        "tags": "[\"Mid-range\", \"American\", \"Bar\"]",
        "price": "$$ - $$$"
    },
    {
        "url": "https://www.tripadvisor.com/Restaurant_Review-g60898-d477814-Reviews-Doc_Chey_s_Noodle_House-Atlanta_Georgia.html",
        "imgs": "[\"https://media-cdn.tripadvisor.com/media/photo-s/0f/18/a8/ee/fried-tofu.jpg\", \"https://media-cdn.tripadvisor.com/media/photo-f/06/0f/c6/72/doc-chey-s-noodle-house.jpg\"]",
        "name": "Doc Chey's Noodle House",
        "address": "1424 N Highland Ave NE, Atlanta, GA 30306-3307",
        "phone": "+1 404-888-0777",
        "id": "4290069470500872",
        "rating": 4,
        "review_count": 120,
        "tags": "[\"Cheap Eats\", \"Chinese\", \"Asian\", \"Thai\"]",
        "price": "$"
    },
    {
        "url": "https://www.tripadvisor.com/Restaurant_Review-g60898-d14020905-Reviews-Mission_Market-Atlanta_Georgia.html",
        "imgs": "[\"https://media-cdn.tripadvisor.com/media/photo-s/12/c3/73/7b/photo3jpg.jpg\", \"https://media-cdn.tripadvisor.com/media/photo-f/12/ce/46/b4/mission-market.jpg\"]",
        "name": "Mission + Market",
        "address": "3550 Lenox Rd NE Suite 550, Three Alliance Center, Atlanta, GA 30326-4334",
        "phone": "+1 404-948-2927",
        "id": "9556451961609007",
        "rating": 4.5,
        "review_count": 60,
        "tags": "[\"Mid-range\", \"American\", \"Seafood\", \"International\"]",
        "price": "$$ - $$$"
    },
    {
        "url": "https://www.tripadvisor.com/Restaurant_Review-g60898-d491898-Reviews-Landmark_Diner-Atlanta_Georgia.html",
        "imgs": "[\"https://media-cdn.tripadvisor.com/media/photo-s/11/76/37/8e/photo0jpg.jpg\", \"https://media-cdn.tripadvisor.com/media/photo-f/05/39/ed/8a/the-landmark-diner.jpg\"]",
        "name": "Landmark Diner",
        "address": "60 Luckie St NW Georgia State University, Atlanta, GA 30303-1904",
        "phone": "+1 404-659-1756",
        "id": "9581827352751804",
        "rating": 3.5,
        "review_count": 239,
        "tags": "[\"Mid-range\", \"American\", \"Diner\", \"Vegetarian Friendly\"]",
        "price": "$$ - $$$"
    },
    {
        "url": "https://www.tripadvisor.com/Restaurant_Review-g60898-d7367462-Reviews-Pijiu_Belly-Atlanta_Georgia.html",
        "imgs": "[\"https://media-cdn.tripadvisor.com/media/photo-s/0a/a2/57/ba/pork-belly-benedict.jpg\", \"https://media-cdn.tripadvisor.com/media/photo-f/07/1f/e2/c7/getlstd-property-photo.jpg\"]",
        "name": "Pijiu Belly",
        "address": "678 10th St NW, Atlanta, GA 30318-5507",
        "phone": "+1 404-343-6828",
        "id": "7095963877939269",
        "rating": 4.5,
        "review_count": 32,
        "tags": "[\"Mid-range\", \"American\", \"Bar\", \"Asian\"]",
        "price": "$$ - $$$"
    },
    {
        "url": "https://www.tripadvisor.com/Restaurant_Review-g60898-d21129565-Reviews-Delbar_Middle_Eastern-Atlanta_Georgia.html",
        "imgs": "[\"https://media-cdn.tripadvisor.com/media/photo-f/1d/cf/cd/00/caption.jpg\", \"https://media-cdn.tripadvisor.com/media/photo-s/1c/30/a5/5b/photo1jpg.jpg\"]",
        "name": "Delbar Middle Eastern",
        "address": "870 Inman Village Pkwy NE Suite 1, Atlanta, GA 30307-5543",
        "phone": "+1 404-500-1444",
        "id": "2163158868353920",
        "rating": 4.5,
        "review_count": 26,
        "tags": "[\"Mid-range\", \"Mediterranean\", \"Middle Eastern\", \"Israeli\"]",
        "price": "$$ - $$$"
    },
    {
        "url": "https://www.tripadvisor.com/Restaurant_Review-g60898-d491806-Reviews-Ruscello-Atlanta_Georgia.html",
        "imgs": "[\"https://media-cdn.tripadvisor.com/media/photo-s/0a/77/be/b2/the-tuscan-salmon-vegetables.jpg\", \"https://media-cdn.tripadvisor.com/media/photo-s/07/c4/d1/80/bar.jpg\"]",
        "name": "Ruscello",
        "address": "4390 Ashford Dunwoody Rd NE Perimeter Mall, Atlanta, GA 30346",
        "phone": "+1 770-350-4817",
        "id": "1412236585526008",
        "rating": 4.5,
        "review_count": 43,
        "tags": "[\"Mid-range\", \"American\", \"Vegetarian Friendly\", \"Vegan Options\"]",
        "price": "$$ - $$$"
    },
    {
        "url": "https://www.tripadvisor.com/Restaurant_Review-g60898-d12822976-Reviews-Kula-Atlanta_Georgia.html",
        "imgs": "[\"https://media-cdn.tripadvisor.com/media/photo-f/10/df/9d/df/photo0jpg.jpg\", \"https://media-cdn.tripadvisor.com/media/photo-s/10/d0/5d/19/kula-atlanta.jpg\"]",
        "name": "Kula",
        "address": "6035 Peachtree Rd, Atlanta, GA 30360-3230",
        "phone": "+1 470-255-2071",
        "id": "316040901654429",
        "rating": 4.5,
        "review_count": 29,
        "tags": "[\"Mid-range\", \"Japanese\", \"Sushi\", \"Asian\"]",
        "price": "$$ - $$$"
    },
    {
        "url": "https://www.tripadvisor.com/Restaurant_Review-g60898-d4916827-Reviews-Hovan_Gourmet-Atlanta_Georgia.html",
        "imgs": "[\"https://media-cdn.tripadvisor.com/media/photo-s/09/1e/58/33/caption.jpg\"]",
        "name": "Hovan Gourmet",
        "address": "2148 Johnson Ferry Rd NE, Atlanta, GA 30319-2558",
        "phone": "+1 770-396-1770",
        "id": "8279980220799775",
        "rating": 4.5,
        "review_count": 31,
        "tags": "[\"Cheap Eats\", \"Mediterranean\", \"Greek\", \"Middle Eastern\"]",
        "price": "$"
    },
    {
        "url": "https://www.tripadvisor.com/Restaurant_Review-g60898-d15680645-Reviews-Gu_s_Kitchen-Atlanta_Georgia.html",
        "imgs": "[\"https://media-cdn.tripadvisor.com/media/photo-f/16/6c/71/35/fat-noodles-with-a-similar.jpg\", \"https://media-cdn.tripadvisor.com/media/photo-s/25/8f/72/8f/szechuan-green-beans.jpg\"]",
        "name": "Gu's Kitchen",
        "address": "4897 Buford Hwy Suite 104, Atlanta, GA 30341-3667",
        "phone": "+1 470-299-2388",
        "id": "40940955332417",
        "rating": 4.5,
        "review_count": 28,
        "tags": "[\"Mid-range\", \"Chinese\", \"Asian\", \"Szechuan\"]",
        "price": "$$ - $$$"
    },
    {
        "url": "https://www.tripadvisor.com/Restaurant_Review-g60898-d1308732-Reviews-Vickery_s_Bar_Grill_Glenwood_Park-Atlanta_Georgia.html",
        "imgs": "[\"https://media-cdn.tripadvisor.com/media/photo-f/03/0a/c9/9e/vickery-s-bar-grill-glenwood.jpg\", \"https://media-cdn.tripadvisor.com/media/photo-f/02/f2/0a/e8/vickery-s-bar-grill-glenwood.jpg\"]",
        "name": "Vickery's Bar & Grill - Glenwood Park",
        "address": "933 Garrett St SE, Atlanta, GA 30316-6821",
        "phone": "+1 404-627-8818",
        "id": "647558194051314",
        "rating": 4.5,
        "review_count": 51,
        "tags": "[\"Mid-range\", \"American\", \"Bar\"]",
        "price": "$$ - $$$"
    },
    {
        "url": "https://www.tripadvisor.com/Restaurant_Review-g60898-d4170139-Reviews-Voya_Bistro-Atlanta_Georgia.html",
        "imgs": "[\"https://media-cdn.tripadvisor.com/media/photo-s/0e/0d/06/7d/voya-bistro.jpg\", \"https://media-cdn.tripadvisor.com/media/photo-s/04/07/02/84/voya-bistro.jpg\"]",
        "name": "Voya Bistro",
        "address": "4711 Best Road Atlanta Airport Marriott, Atlanta, GA 30337",
        "phone": "+1 404-766-7900",
        "id": "6528226937532648",
        "rating": 4,
        "review_count": 84,
        "tags": "[\"Mid-range\", \"American\", \"Sushi\"]",
        "price": "$$ - $$$"
    },
    {
        "url": "https://www.tripadvisor.com/Restaurant_Review-g60898-d2667054-Reviews-California_Pizza_Kitchen-Atlanta_Georgia.html",
        "imgs": "[\"https://media-cdn.tripadvisor.com/media/photo-f/1a/1f/9c/50/asian-cauliflower-so.jpg\", \"https://media-cdn.tripadvisor.com/media/photo-s/0e/0a/97/c8/side-salad-and-veggie.jpg\"]",
        "name": "California Pizza Kitchen",
        "address": "264 19th St NW Ste. 2150, Atlanta, GA 30363-1135",
        "phone": "+1 404-249-7034",
        "id": "3270088598051124",
        "rating": 4,
        "review_count": 86,
        "tags": "[\"Mid-range\", \"American\", \"Pizza\", \"Vegetarian Friendly\"]",
        "price": "$$ - $$$"
    },
    {
        "url": "https://www.tripadvisor.com/Restaurant_Review-g60898-d16801945-Reviews-Parkwoods-Atlanta_Georgia.html",
        "imgs": "[\"https://media-cdn.tripadvisor.com/media/photo-s/16/d2/9f/fa/serving-breakfast-lunch.jpg\", \"https://media-cdn.tripadvisor.com/media/photo-s/16/d2/a0/90/seared-red-snapper.jpg\"]",
        "name": "Parkwoods",
        "address": "4355 Ashford Dunwoody Rd NE, Atlanta, GA 30346-1503",
        "phone": "+1 678-822-9353",
        "id": "7077969481811541",
        "rating": 4.5,
        "review_count": 19,
        "tags": "[\"Mid-range\", \"American\"]",
        "price": "$$ - $$$"
    },
    {
        "url": "https://www.tripadvisor.com/Restaurant_Review-g60898-d7046416-Reviews-Painted_pin_atlanta_ga-Atlanta_Georgia.html",
        "imgs": "[\"https://media-cdn.tripadvisor.com/media/photo-s/15/2d/76/85/painted-pin-atlanta-ga.jpg\", \"https://media-cdn.tripadvisor.com/media/photo-f/07/93/c0/2b/the-turkey-club.jpg\"]",
        "name": "painted pin atlanta ga",
        "address": "Miami Circle, Atlanta, GA",
        "phone": "+1 404-814-8736",
        "id": "16453749114035",
        "rating": 4,
        "review_count": 59,
        "tags": "[\"Mid-range\", \"American\", \"Bar\"]",
        "price": "$$ - $$$"
    },
    {
        "url": "https://www.tripadvisor.com/Restaurant_Review-g60898-d4810657-Reviews-Meehan_s_Public_House_Atlantic_Station-Atlanta_Georgia.html",
        "imgs": "[\"https://media-cdn.tripadvisor.com/media/photo-s/0f/18/f7/a5/brunch.jpg\", \"https://media-cdn.tripadvisor.com/media/photo-s/0f/18/f7/aa/fried-pickles.jpg\"]",
        "name": "Meehan's Public House - Atlantic Station",
        "address": "232 19th St NW Ste 7165, Atlanta, GA 30363-1130",
        "phone": "+1 404-249-7812",
        "id": "4453656568548370",
        "rating": 4,
        "review_count": 102,
        "tags": "[\"Mid-range\", \"American\", \"Irish\", \"Bar\"]",
        "price": "$$ - $$$"
    },
    {
        "url": "https://www.tripadvisor.com/Restaurant_Review-g60898-d1052136-Reviews-La_Parrilla_Mexican_Restaurant-Atlanta_Georgia.html",
        "imgs": "[\"https://media-cdn.tripadvisor.com/media/photo-s/04/a6/ce/92/la-parrilla-mexican-restaurant.jpg\", \"https://media-cdn.tripadvisor.com/media/photo-s/04/a6/ce/b4/la-parrilla-mexican-restaurant.jpg\"]",
        "name": "La Parrilla Mexican Restaurant",
        "address": "1801 Howell Mill Rd NW Suite 420, Atlanta, GA 30318-0911",
        "phone": "+1 404-603-9091",
        "id": "2886487288281985",
        "rating": 4,
        "review_count": 81,
        "tags": "[\"Mid-range\", \"Mexican\", \"Southwestern\", \"Vegetarian Friendly\"]",
        "price": "$$ - $$$"
    },
    {
        "url": "https://www.tripadvisor.com/Restaurant_Review-g60898-d13894225-Reviews-Milk_and_honey-Atlanta_Georgia.html",
        "imgs": "[\"https://media-cdn.tripadvisor.com/media/photo-s/12/d6/96/1e/20180503-132135-largejpg.jpg\", \"https://media-cdn.tripadvisor.com/media/photo-s/12/98/6a/be/half-milk-honey-half.jpg\"]",
        "name": "Milk and honey",
        "address": "5495 Cascade Rd SW Suite 100, Atlanta, GA 30331-7359",
        "phone": "+1 404-968-9266",
        "id": "4298870692010516",
        "rating": 4,
        "review_count": 62,
        "tags": "[\"Mid-range\", \"American\", \"Vegetarian Friendly\", \"Vegan Options\"]",
        "price": "$$ - $$$"
    },
    {
        "url": "https://www.tripadvisor.com/Restaurant_Review-g60898-d3224582-Reviews-Ammazza-Atlanta_Georgia.html",
        "imgs": "[\"https://media-cdn.tripadvisor.com/media/photo-f/06/25/1b/ae/ammazza-atlanta.jpg\", \"https://media-cdn.tripadvisor.com/media/photo-s/04/2a/37/26/ammazza.jpg\"]",
        "name": "Ammazza",
        "address": "591 Edgewood Ave SE, Atlanta, GA 30312-1935",
        "phone": "+1 404-228-1036",
        "id": "226958246239177",
        "rating": 4,
        "review_count": 82,
        "tags": "[\"Mid-range\", \"Italian\", \"Pizza\", \"Vegetarian Friendly\"]",
        "price": "$$ - $$$"
    },
    {
        "url": "https://www.tripadvisor.com/Restaurant_Review-g60898-d435208-Reviews-Fellini_s_Pizza-Atlanta_Georgia.html",
        "imgs": "[\"https://media-cdn.tripadvisor.com/media/photo-s/0e/15/17/fd/photo0jpg.jpg\", \"https://media-cdn.tripadvisor.com/media/photo-s/16/a2/d0/25/photo0jpg.jpg\"]",
        "name": "Fellini's Pizza",
        "address": "1634 McLendon Ave NE, Atlanta, GA 30307-2153",
        "phone": "+1 404-687-9190",
        "id": "9261452943823984",
        "rating": 4.5,
        "review_count": 46,
        "tags": "[\"Mid-range\", \"Pizza\", \"Vegetarian Friendly\"]",
        "price": "$$ - $$$"
    },
    {
        "url": "https://www.tripadvisor.com/Restaurant_Review-g60898-d435273-Reviews-Willy_s_Mexicana_Grill-Atlanta_Georgia.html",
        "imgs": "[\"https://media-cdn.tripadvisor.com/media/photo-s/16/96/22/0b/02-24-19.jpg\", \"https://media-cdn.tripadvisor.com/media/photo-f/02/1e/f1/f4/willy-s-mexicana-grill.jpg\"]",
        "name": "Willy's Mexicana Grill",
        "address": "235 Peachtree St NE, Atlanta, GA 30303-1401",
        "phone": "+1 404-524-0821",
        "id": "3437405121642578",
        "rating": 4,
        "review_count": 68,
        "tags": "[\"Cheap Eats\", \"Mexican\", \"Southwestern\", \"Fast Food\"]",
        "price": "$"
    },
    {
        "url": "https://www.tripadvisor.com/Restaurant_Review-g60898-d12231961-Reviews-Pho_King-Atlanta_Georgia.html",
        "imgs": "[\"https://media-cdn.tripadvisor.com/media/photo-f/16/c4/92/16/photo0jpg.jpg\", \"https://media-cdn.tripadvisor.com/media/photo-s/13/0f/6d/88/beef-brisket-beef-flank.jpg\"]",
        "name": "Pho King",
        "address": "950 W Peachtree St NW, Atlanta, GA 30309-3846",
        "phone": "+1 404-565-1953",
        "id": "6594694854119687",
        "rating": 4.5,
        "review_count": 27,
        "tags": "[\"Cheap Eats\", \"Asian\", \"Vietnamese\", \"Soups\"]",
        "price": "$"
    }
]