[
    {
        "url": "https://www.tripadvisor.com/Restaurant_Review-g60713-d4572873-Reviews-Crab_Station_at_Fishermans_Wharf-San_Francisco_California.html",
        "imgs": "[\"https://media-cdn.tripadvisor.com/media/photo-f/10/60/a7/89/fritures.jpg\", \"https://media-cdn.tripadvisor.com/media/photo-s/29/62/e3/4a/caption.jpg\"]",
        "name": "Crab Station at Fishermans Wharf",
        "address": "2803 Taylor St Suite 2, San Francisco, CA 94133-1048",
        "phone": "+1 415-474-8796",
        "id": "5861033337682938",
        "rating": 4,
        "review_count": 240,
        "tags": "[\"Mid-range\", \"American\", \"Seafood\", \"Fast Food\"]",
        "price": "$$ - $$$"
    },
    {
        "url": "https://www.tripadvisor.com/Restaurant_Review-g60713-d9838725-Reviews-Mensho_Tokyo-San_Francisco_California.html",
        "imgs": "[\"https://media-cdn.tripadvisor.com/media/photo-s/17/12/b9/b0/mushroom-chips-very-oily.jpg\", \"https://media-cdn.tripadvisor.com/media/photo-f/0a/7b/80/97/photo1jpg.jpg\"]",
        "name": "Mensho Tokyo",
        "address": "672 Geary St, San Francisco, CA 94102-1647",
        "phone": "+1 415-800-8345",
        "id": "669866098557679",
        "rating": 4.5,
        "review_count": 97,
        "tags": "[\"Mid-range\", \"Japanese\", \"Asian\", \"Soups\"]",
        "price": "$$ - $$$"
    },
    {
        "url": "https://www.tripadvisor.com/Restaurant_Review-g60713-d7684470-Reviews-AL_s_Place-San_Francisco_California.html",
        "imgs": "[\"https://media-cdn.tripadvisor.com/media/photo-s/14/91/c1/e7/the-campanelle.jpg\", \"https://media-cdn.tripadvisor.com/media/photo-f/0f/d5/32/a8/photo5jpg.jpg\"]",
        "name": "AL's Place",
        "address": "1499 Valencia St 26th Street, San Francisco, CA 94110-3716",
        "phone": "+1 415-416-6136",
        "id": "6963088281648446",
        "rating": 4,
        "review_count": 183,
        "tags": "[\"Mid-range\", \"American\", \"Vegetarian Friendly\", \"Vegan Options\"]",
        "price": "$$ - $$$"
    },
    {
        "url": "https://www.tripadvisor.com/Restaurant_Review-g60713-d13130035-Reviews-International_Smoke_San_Francisco-San_Francisco_California.html",
        "imgs": "[\"https://media-cdn.tripadvisor.com/media/photo-s/18/b2/c4/22/ribs.jpg\", \"https://media-cdn.tripadvisor.com/media/photo-s/18/b2/c5/07/curry-soup.jpg\"]",
        "name": "International Smoke San Francisco",
        "address": "301 Mission St. Millennium Tower, San Francisco, CA 94105",
        "phone": "+1 415-660-2656",
        "id": "5492384288509436",
        "rating": 4,
        "review_count": 139,
        "tags": "[\"Mid-range\", \"American\", \"Bar\", \"International\"]",
        "price": "$$ - $$$"
    },
    {
        "url": "https://www.tripadvisor.com/Restaurant_Review-g60713-d3235657-Reviews-Bask-San_Francisco_California.html",
        "imgs": "[\"https://media-cdn.tripadvisor.com/media/photo-f/19/fa/66/ea/octopus-the-best.jpg\", \"https://media-cdn.tripadvisor.com/media/photo-f/22/00/a3/d5/perfect-for-groups.jpg\"]",
        "name": "Bask",
        "address": "42 Columbus Ave, San Francisco, CA 94111-2102",
        "phone": "+1 415-392-2275",
        "id": "8863417255266365",
        "rating": 4,
        "review_count": 165,
        "tags": "[\"Mid-range\", \"Mediterranean\", \"Spanish\", \"Basque\"]",
        "price": "$$ - $$$"
    },
    {
        "url": "https://www.tripadvisor.com/Restaurant_Review-g60713-d602773-Reviews-Capurro_s_Restaurant_and_Bar-San_Francisco_California.html",
        "imgs": "[\"https://media-cdn.tripadvisor.com/media/photo-s/0d/27/39/4b/photo2jpg.jpg\", \"https://media-cdn.tripadvisor.com/media/photo-s/01/8e/80/91/capurro-s-restaurant.jpg\"]",
        "name": "Capurro's Restaurant and Bar",
        "address": "498 Jefferson St, San Francisco, CA 94109-1315",
        "phone": "+1 415-771-9371",
        "id": "2618945131436108",
        "rating": 3.5,
        "review_count": 812,
        "tags": "[\"Mid-range\", \"American\", \"Bar\", \"Seafood\"]",
        "price": "$$ - $$$"
    },
    {
        "url": "https://www.tripadvisor.com/Restaurant_Review-g60713-d9788372-Reviews-Leo_s_Oyster_Bar-San_Francisco_California.html",
        "imgs": "[\"https://media-cdn.tripadvisor.com/media/photo-f/17/6a/6e/fb/photo1jpg.jpg\", \"https://media-cdn.tripadvisor.com/media/photo-s/0a/57/c7/90/leo-s-oyster-bar.jpg\"]",
        "name": "Leo\u2019s Oyster Bar",
        "address": "568 Sacramento St, San Francisco, CA 94111-3024",
        "phone": "+1 415-872-9982",
        "id": "9604559913908823",
        "rating": 4.5,
        "review_count": 78,
        "tags": "[\"Fine Dining\", \"American\", \"Seafood\", \"Gluten Free Options\"]",
        "price": "$$$$"
    },
    {
        "url": "https://www.tripadvisor.com/Restaurant_Review-g60713-d1067507-Reviews-Miss_Saigon-San_Francisco_California.html",
        "imgs": "[\"https://media-cdn.tripadvisor.com/media/photo-f/07/ad/7f/d5/miss-saigon.jpg\", \"https://media-cdn.tripadvisor.com/media/photo-s/16/a3/68/c0/miss-saigon.jpg\"]",
        "name": "Miss Saigon",
        "address": "100 6th St, San Francisco, CA 94103-2815",
        "phone": "+1 415-522-0332",
        "id": "3626919933889420",
        "rating": 4.5,
        "review_count": 101,
        "tags": "[\"Cheap Eats\", \"Asian\", \"Vietnamese\", \"Soups\"]",
        "price": "$"
    },
    {
        "url": "https://www.tripadvisor.com/Restaurant_Review-g60713-d7747195-Reviews-Dragon_Beaux-San_Francisco_California.html",
        "imgs": "[\"https://media-cdn.tripadvisor.com/media/photo-f/19/f0/09/8e/scallop-siu-mai.jpg\", \"https://media-cdn.tripadvisor.com/media/photo-s/19/f0/0b/ac/dim-sum-perfection.jpg\"]",
        "name": "Dragon Beaux",
        "address": "5700 Geary Blvd, San Francisco, CA 94121-2112",
        "phone": "+1 415-333-8899",
        "id": "2498655562294345",
        "rating": 4,
        "review_count": 110,
        "tags": "[\"Mid-range\", \"Chinese\", \"Seafood\", \"Asian\"]",
        "price": "$$ - $$$"
    },
    {
        "url": "https://www.tripadvisor.com/Restaurant_Review-g60713-d372070-Reviews-Caffe_Sport-San_Francisco_California.html",
        "imgs": "[\"https://media-cdn.tripadvisor.com/media/photo-f/08/da/29/43/caffe-sport.jpg\", \"https://media-cdn.tripadvisor.com/media/photo-f/0d/ed/74/c4/we-ben-there-in-a-large.jpg\"]",
        "name": "Caffe Sport",
        "address": "574 Green St, San Francisco, CA 94133-3920",
        "phone": "+1 415-981-1251",
        "id": "463657582861398",
        "rating": 4,
        "review_count": 206,
        "tags": "[\"Mid-range\", \"Italian\", \"Vegetarian Friendly\", \"Gluten Free Options\"]",
        "price": "$$ - $$$"
    },
    {
        "url": "https://www.tripadvisor.com/Restaurant_Review-g60713-d354001-Reviews-Cafe_Jacqueline-San_Francisco_California.html",
        "imgs": "[\"https://media-cdn.tripadvisor.com/media/photo-s/03/92/5d/56/cafe-jacqueline.jpg\", \"https://media-cdn.tripadvisor.com/media/photo-s/03/92/5d/57/cafe-jacqueline.jpg\"]",
        "name": "Cafe Jacqueline",
        "address": "1454 Grant Ave, San Francisco, CA 94133-3304",
        "phone": "+1 415-981-5565",
        "id": "5885786328578073",
        "rating": 4.5,
        "review_count": 123,
        "tags": "[\"Fine Dining\", \"French\", \"European\", \"Vegetarian Friendly\"]",
        "price": "$$$$"
    },
    {
        "url": "https://www.tripadvisor.com/Restaurant_Review-g60713-d8610396-Reviews-1428_HAIGHT_Patio_Cafe_Crepery-San_Francisco_California.html",
        "imgs": "[\"https://media-cdn.tripadvisor.com/media/photo-s/14/a4/99/a6/20180914-103108-largejpg.jpg\", \"https://media-cdn.tripadvisor.com/media/photo-s/0e/05/93/03/panquecas.jpg\"]",
        "name": "1428 HAIGHT Patio Cafe & Crepery",
        "address": "1428 Haight St Bairro Hippie, San Francisco, CA 94117-2911",
        "phone": "+1 415-864-8484",
        "id": "1877830752303782",
        "rating": 4.5,
        "review_count": 77,
        "tags": "[\"Mid-range\", \"American\", \"Cafe\", \"Vegetarian Friendly\"]",
        "price": "$$ - $$$"
    },
    {
        "url": "https://www.tripadvisor.com/Restaurant_Review-g60713-d602167-Reviews-Jake_s_Steaks-San_Francisco_California.html",
        "imgs": "[\"https://media-cdn.tripadvisor.com/media/photo-s/0e/44/0f/f9/cheesesteaks-salad.jpg\", \"https://media-cdn.tripadvisor.com/media/photo-s/01/b7/93/fb/yummy-buffalo-wings.jpg\"]",
        "name": "Jake's Steaks",
        "address": "3301 Buchanan St Between Chessnut & Lombard, San Francisco, CA 94123-2801",
        "phone": "+1 415-922-2211",
        "id": "9550832834282446",
        "rating": 4.5,
        "review_count": 109,
        "tags": "[\"Cheap Eats\", \"American\", \"Beer restaurants\"]",
        "price": "$"
    },
    {
        "url": "https://www.tripadvisor.com/Restaurant_Review-g60713-d3439205-Reviews-Cafe_Mystique-San_Francisco_California.html",
        "imgs": "[\"https://media-cdn.tripadvisor.com/media/photo-f/12/54/3c/8d/20180314-130103-largejpg.jpg\", \"https://media-cdn.tripadvisor.com/media/photo-s/03/f7/ba/af/rissoto_rotated_90.jpg\"]",
        "name": "Cafe Mystique",
        "address": "464 Castro St, San Francisco, CA 94114-2020",
        "phone": "+1 415-865-9963",
        "id": "7802783013318755",
        "rating": 4,
        "review_count": 152,
        "tags": "[\"Mid-range\", \"American\", \"Mediterranean\", \"Vegetarian Friendly\"]",
        "price": "$$ - $$$"
    },
    {
        "url": "https://www.tripadvisor.com/Restaurant_Review-g60713-d370457-Reviews-Balboa_Cafe-San_Francisco_California.html",
        "imgs": "[\"https://media-cdn.tripadvisor.com/media/photo-f/0c/60/6b/97/balboa-cafe.jpg\", \"https://media-cdn.tripadvisor.com/media/photo-f/01/a8/cd/e4/balboa-cafe.jpg\"]",
        "name": "Balboa Cafe",
        "address": "3199 Fillmore St, San Francisco, CA 94123-3451",
        "phone": "+1 415-921-3944",
        "id": "2433813958110093",
        "rating": 4,
        "review_count": 157,
        "tags": "[\"Mid-range\", \"American\", \"Bar\", \"Gluten Free Options\"]",
        "price": "$$ - $$$"
    },
    {
        "url": "https://www.tripadvisor.com/Restaurant_Review-g60713-d5081938-Reviews-The_Grubstake-San_Francisco_California.html",
        "imgs": "[\"https://media-cdn.tripadvisor.com/media/photo-s/17/73/4f/3d/super-johnny-burger.jpg\", \"https://media-cdn.tripadvisor.com/media/photo-f/0b/0d/22/e7/our-super-johnny-burger.jpg\"]",
        "name": "The Grubstake",
        "address": "1525 Pine St, San Francisco, CA 94109-4611",
        "phone": "+1 415-228-8420",
        "id": "7283510815771275",
        "rating": 4,
        "review_count": 204,
        "tags": "[\"Mid-range\", \"American\", \"Bar\", \"Diner\"]",
        "price": "$$ - $$$"
    },
    {
        "url": "https://www.tripadvisor.com/Restaurant_Review-g60713-d10954375-Reviews-Nightbird-San_Francisco_California.html",
        "imgs": "[\"https://media-cdn.tripadvisor.com/media/photo-f/12/f8/00/97/nightbird.jpg\", \"https://media-cdn.tripadvisor.com/media/photo-s/0f/9b/ad/36/smoked-ricotta-agnolotti.jpg\"]",
        "name": "Nightbird",
        "address": "330 Gough St, San Francisco, CA 94102-5115",
        "phone": "+1 415-829-7565",
        "id": "6468579177678831",
        "rating": 5,
        "review_count": 49,
        "tags": "[\"Fine Dining\", \"American\", \"Vegetarian Friendly\", \"Vegan Options\"]",
        "price": "$$$$"
    },
    {
        "url": "https://www.tripadvisor.com/Restaurant_Review-g60713-d360044-Reviews-Basil_Thai_Restaurant_Bar-San_Francisco_California.html",
        "imgs": "[\"https://media-cdn.tripadvisor.com/media/photo-s/1b/8a/e8/a4/banner.jpg\", \"https://media-cdn.tripadvisor.com/media/photo-f/18/ae/00/2e/photo0jpg.jpg\"]",
        "name": "Basil - Thai Restaurant & Bar",
        "address": "1175 Folsom St Between 7th & 8th Street, San Francisco, CA 94103-3930",
        "phone": "+1 415-552-8999",
        "id": "9446090635367686",
        "rating": 4,
        "review_count": 142,
        "tags": "[\"Mid-range\", \"Asian\", \"Thai\", \"Vegetarian Friendly\"]",
        "price": "$$ - $$$"
    },
    {
        "url": "https://www.tripadvisor.com/Restaurant_Review-g60713-d966759-Reviews-Front_Porch-San_Francisco_California.html",
        "imgs": "[\"https://media-cdn.tripadvisor.com/media/photo-f/0d/16/0e/84/img-20160924-182215-largejpg.jpg\", \"https://media-cdn.tripadvisor.com/media/photo-f/06/08/df/7d/front-porch.jpg\"]",
        "name": "Front Porch",
        "address": "65 29th St, San Francisco, CA 94110-4910",
        "phone": "+1 415-695-7800",
        "id": "3003147038329909",
        "rating": 4,
        "review_count": 137,
        "tags": "[\"Mid-range\", \"American\", \"Bar\", \"Pub\"]",
        "price": "$$ - $$$"
    },
    {
        "url": "https://www.tripadvisor.com/Restaurant_Review-g60713-d11802194-Reviews-El_Techo-San_Francisco_California.html",
        "imgs": "[\"https://media-cdn.tripadvisor.com/media/photo-s/13/b4/12/93/veg-skewers.jpg\", \"https://media-cdn.tripadvisor.com/media/photo-s/0e/7f/56/43/photo1jpg.jpg\"]",
        "name": "El Techo",
        "address": "2516 Mission Street Penthouse Of The Building, San Francisco, CA 94110",
        "phone": "+1 415-550-6970",
        "id": "4429519522469356",
        "rating": 4,
        "review_count": 103,
        "tags": "[\"Mid-range\", \"Mexican\", \"Latin\", \"Vegetarian Friendly\"]",
        "price": "$$ - $$$"
    },
    {
        "url": "https://www.tripadvisor.com/Restaurant_Review-g60713-d480461-Reviews-Golden_Coffee_Shop-San_Francisco_California.html",
        "imgs": "[\"https://media-cdn.tripadvisor.com/media/photo-s/0c/6c/d2/51/photo2jpg.jpg\", \"https://media-cdn.tripadvisor.com/media/photo-f/02/22/89/eb/pancakes-sooooo-good.jpg\"]",
        "name": "Golden Coffee Shop",
        "address": "901 Sutter St, San Francisco, CA 94109-6023",
        "phone": "+1 415-922-0537",
        "id": "268833669221226",
        "rating": 4.5,
        "review_count": 110,
        "tags": "[\"Cheap Eats\", \"American\", \"Cafe\", \"Diner\"]",
        "price": "$"
    },
    {
        "url": "https://www.tripadvisor.com/Restaurant_Review-g60713-d360155-Reviews-Zingari_Ristorante_Jazz_Room-San_Francisco_California.html",
        "imgs": "[\"https://media-cdn.tripadvisor.com/media/photo-f/1c/56/71/54/a-beautiful-ristorante.jpg\", \"https://media-cdn.tripadvisor.com/media/photo-s/1b/10/d9/c3/venetian-room.jpg\"]",
        "name": "Zingari Ristorante & Jazz Room",
        "address": "501 Post Street, San Francisco, CA 94102",
        "phone": "+1 415-885-8850",
        "id": "2558548473730368",
        "rating": 3.5,
        "review_count": 542,
        "tags": "[\"Fine Dining\", \"Italian\", \"Steakhouse\", \"Seafood\"]",
        "price": "$$$$"
    },
    {
        "url": "https://www.tripadvisor.com/Restaurant_Review-g60713-d947691-Reviews-Bursa-San_Francisco_California.html",
        "imgs": "[\"https://media-cdn.tripadvisor.com/media/photo-s/0f/20/d2/4a/warm-romantic-atmosphere.jpg\", \"https://media-cdn.tripadvisor.com/media/photo-f/1b/4b/df/7d/we-are-discounting-our.jpg\"]",
        "name": "Bursa",
        "address": "60 W Portal Ave 1/2 block from West Portal Station, San Francisco, CA 94127-1304",
        "phone": "+1 415-564-4006",
        "id": "5250504395244659",
        "rating": 4.5,
        "review_count": 82,
        "tags": "[\"Mid-range\", \"Mediterranean\", \"Turkish\", \"Middle Eastern\"]",
        "price": "$$ - $$$"
    },
    {
        "url": "https://www.tripadvisor.com/Restaurant_Review-g60713-d1869042-Reviews-Sushi_Toni-San_Francisco_California.html",
        "imgs": "[\"https://media-cdn.tripadvisor.com/media/photo-s/0b/79/1f/a8/sweet-shrimp-nigiri.jpg\", \"https://media-cdn.tripadvisor.com/media/photo-f/01/f1/09/12/sushi-toni.jpg\"]",
        "name": "Sushi Toni",
        "address": "733 Bush St, San Francisco, CA 94108-3402",
        "phone": "+1 415-986-8664",
        "id": "4434653445449867",
        "rating": 4,
        "review_count": 153,
        "tags": "[\"Mid-range\", \"Japanese\", \"Sushi\", \"Asian\"]",
        "price": "$$ - $$$"
    },
    {
        "url": "https://www.tripadvisor.com/Restaurant_Review-g60713-d3460794-Reviews-Mission_Rock_Resort-San_Francisco_California.html",
        "imgs": "[\"https://media-cdn.tripadvisor.com/media/photo-f/0e/05/94/51/photo6jpg.jpg\", \"https://media-cdn.tripadvisor.com/media/photo-s/05/aa/c3/e4/mission-rock-resort.jpg\"]",
        "name": "Mission Rock Resort",
        "address": "817 Terry a Francois Blvd, San Francisco, CA 94158-2209",
        "phone": "+1 415-701-7625",
        "id": "8546585533307203",
        "rating": 4,
        "review_count": 142,
        "tags": "[\"Mid-range\", \"American\", \"Bar\", \"Seafood\"]",
        "price": "$$ - $$$"
    },
    {
        "url": "https://www.tripadvisor.com/Restaurant_Review-g60713-d372215-Reviews-The_Crepe_House-San_Francisco_California.html",
        "imgs": "[\"https://media-cdn.tripadvisor.com/media/photo-s/13/eb/01/2e/20180730-083048-largejpg.jpg\", \"https://media-cdn.tripadvisor.com/media/photo-f/01/27/92/02/san-francisco.jpg\"]",
        "name": "The Crepe House",
        "address": "1755 Polk St, San Francisco, CA 94109-3616",
        "phone": "+1 415-441-2421",
        "id": "9643155379110729",
        "rating": 4,
        "review_count": 98,
        "tags": "[\"Cheap Eats\", \"American\", \"Cafe\", \"Healthy\"]",
        "price": "$"
    },
    {
        "url": "https://www.tripadvisor.com/Restaurant_Review-g60713-d2474852-Reviews-Viking_s_Giant_Subs-San_Francisco_California.html",
        "imgs": "[\"https://media-cdn.tripadvisor.com/media/photo-s/18/cf/1e/4c/viking-s-giant-subs.jpg\", \"https://media-cdn.tripadvisor.com/media/photo-s/0e/94/bc/f2/waiting-for-my-sub.jpg\"]",
        "name": "Viking's Giant Subs",
        "address": "1418 Lombard St, San Francisco, CA 94123-3112",
        "phone": "+1 415-673-5619",
        "id": "1474631774680202",
        "rating": 4.5,
        "review_count": 80,
        "tags": "[\"Cheap Eats\", \"American\", \"Vegetarian Friendly\"]",
        "price": "$"
    },
    {
        "url": "https://www.tripadvisor.com/Restaurant_Review-g60713-d368745-Reviews-Morning_Due_Cafe-San_Francisco_California.html",
        "imgs": "[\"https://media-cdn.tripadvisor.com/media/photo-f/17/9f/18/6d/inside-decor.jpg\", \"https://media-cdn.tripadvisor.com/media/photo-s/29/8b/54/c1/caption.jpg\"]",
        "name": "Morning Due Cafe",
        "address": "3698 17th St, San Francisco, CA 94114-2625",
        "phone": "+1 415-621-7156",
        "id": "897397747688322",
        "rating": 4.5,
        "review_count": 84,
        "tags": "[\"Mid-range\", \"American\", \"Cafe\", \"Vegetarian Friendly\"]",
        "price": "$$ - $$$"
    },
    {
        "url": "https://www.tripadvisor.com/Restaurant_Review-g60713-d537838-Reviews-Vicoletto_San_Francisco-San_Francisco_California.html",
        "imgs": "[\"https://media-cdn.tripadvisor.com/media/photo-f/10/51/f8/f5/photo2jpg.jpg\", \"https://media-cdn.tripadvisor.com/media/photo-s/04/82/bc/9f/gluten-free-rigatoni.jpg\"]",
        "name": "Vicoletto San Francisco",
        "address": "550 Green St, San Francisco, CA 94133-3920",
        "phone": "+1 415-433-5800",
        "id": "7297946014476795",
        "rating": 4.5,
        "review_count": 178,
        "tags": "[\"Mid-range\", \"Italian\", \"Vegetarian Friendly\", \"Gluten Free Options\"]",
        "price": "$$ - $$$"
    },
    {
        "url": "https://www.tripadvisor.com/Restaurant_Review-g60713-d8135368-Reviews-Turntable_at_Lord_Stanley-San_Francisco_California.html",
        "imgs": "[\"https://media-cdn.tripadvisor.com/media/photo-s/12/bd/e8/82/photo-by-antoinette-bruno.jpg\", \"https://media-cdn.tripadvisor.com/media/photo-s/12/bd/ea/92/photo-by-aubrie-pick.jpg\"]",
        "name": "Turntable at Lord Stanley",
        "address": "2065 Polk St, San Francisco, CA 94109-2519",
        "phone": "+1 415-518-2624",
        "id": "31780606198011",
        "rating": 4.5,
        "review_count": 86,
        "tags": "[\"Fine Dining\", \"American\", \"Vegetarian Friendly\", \"Vegan Options\"]",
        "price": "$$$$"
    }
]